Symqui-0.2.dev0.dist-info/DESCRIPTION.rst
Symqui-0.2.dev0.dist-info/METADATA
Symqui-0.2.dev0.dist-info/RECORD
Symqui-0.2.dev0.dist-info/WHEEL
Symqui-0.2.dev0.dist-info/metadata.json
Symqui-0.2.dev0.dist-info/top_level.txt
symqui/__init__.py
