Metadata-Version: 2.0
Name: Symqui
Version: 0.2.dev0
Summary: UNKNOWN
Home-page: https://github.com/suksmono/Symque
Author: Andriyan Suksmono
Author-email: suksmono@yahoo.com
License: Creative Commons Attribution-Noncommercial-Share Alike license
Platform: UNKNOWN
